dots_infrastructure/CalculationServiceHelperFunctions.py
dots_infrastructure/Common.py
dots_infrastructure/Constants.py
dots_infrastructure/DataClasses.py
dots_infrastructure/EsdlHelper.py
dots_infrastructure/EsdlHelperFunctions.py
dots_infrastructure/HelicsFederateHelpers.py
dots_infrastructure/Logger.py
dots_infrastructure/__init__.py
dots_infrastructure/influxdb_connector.py
dots_infrastructure/code_gen/code_gen.py
dots_infrastructure/code_gen/code_meta_data.py
dots_infrastructure/code_gen/test.json
dots_infrastructure/code_gen/test_code_gen.py
dots_infrastructure/code_gen/templates/calculation_service/calculation_service.py.jinja
dots_infrastructure/code_gen/templates/data_classes/cs_data_classes.py.jinja
dots_infrastructure/code_gen/templates/documentation/cs_documentation.md.jinja
dots_infrastructure/test_infra/HelicsMocks.py
dots_infrastructure/test_infra/InfluxDBClientMock.py
dots_infrastructure/test_infra/InfluxDBMock.py
dots_infrastructure-1.0.6.dist-info/METADATA
dots_infrastructure-1.0.6.dist-info/WHEEL
dots_infrastructure-1.0.6.dist-info/licenses/LICENSE
dots_infrastructure-1.0.6.dist-info/RECORD
