Metadata-Version: 2.4
Name: dots_infrastructure
Version: 1.0.6
Summary: A python package containing infrastructure to develop a dots calculation service
Project-URL: Homepage, https://github.com/dots-energy/dots-infrastructure
Project-URL: Issues, https://github.com/dots-energy/dots-infrastructure/issues
Author-email: Leo van Schooten <l.g.t.v.schooten@tue.nl>
License-File: LICENSE
Classifier: License :: OSI Approved :: MIT License
Classifier: Operating System :: OS Independent
Classifier: Programming Language :: Python :: 3
Requires-Python: >=3.12
Requires-Dist: dataclasses-json==0.6.7
Requires-Dist: helics==3.6.1
Requires-Dist: influxdb~=5.3.1
Requires-Dist: jinja2==3.1.6
Requires-Dist: pyesdl==22.11.2
